Workbook
Name Slicer_City: #N/A
Name Slicer_Dining_Type: #N/A
Name Slicer_Month: #N/A

Sheet Data
A1: Order ID | B1: Order date | C1: Month | D1: Quarter | E1: Order Time | F1: Day | G1: Customer ID | H1: Customer Type | I1: Gender | J1: Age Group | K1: Waiter | L1: City | M1: Table No | N1: Dining Type | O1: Payment Method | P1: Food Category | Q1: Item Name | R1: Quantity | S1: Unit Price | T1: Discount % | U1: Tax % | V1: Rating | W1: Total sales | X1: Cost | Y1: Profit | Z1: Unique Customers
A2: ORD0010 | B2: 45685 | C2: Jan | D2: Q1 | E2: 20:45 | F2: Saturday | G2: C040 | H2: Occasional | I2: Female | J2: 18-25 | K2: Lucas | L2: Singapore | M2: 7 | N2: Delivery | O2: Wallet | P2: Seafood | Q2: Fish Tacos | R2: 2 | S2: 3.08 | T2: 10 | U2: 5 | V2: 3 | W2: =Data!$R2*Data!$S2*(1-Data!$T2/100)*(1+Data!$U2/100) -> 5.8212 | X2: =Data!$R2*Data!$S2*50% -> 3.08 | Y2: =Data!$W2-Data!$X2 -> 2.7412 | Z2: =IF(COUNTIF($G$2:G2,G2)=1,1,0) -> 1
A3: ORD0013 | B3: 45662 | C3: Jan | D3: Q1 | E3: 12:00 | F3: Saturday | G3: C148 | H3: New | I3: Female | J3: 26-35 | K3: Ethan | L3: Tokyo | M3: 17 | N3: Dine-In | O3: Card | P3: Desserts | Q3: Chocolate Lava Cake | R3: 2 | S3: 5.67 | T3: 0 | U3: 5 | V3: 4.5 | W3: =Data!$R3*Data!$S3*(1-Data!$T3/100)*(1+Data!$U3/100) -> 11.907 | X3: =Data!$R3*Data!$S3*50% -> 5.67 | Y3: =Data!$W3-Data!$X3 -> 6.237 | Z3: =IF(COUNTIF($G$2:G3,G3)=1,1,0) -> 1
A4: ORD0015 | B4: 45677 | C4: Jan | D4: Q1 | E4: 11:00 | F4: Sunday | G4: C007 | H4: Occasional | I4: Female | J4: 26-35 | K4: Lucas | L4: Paris | M4: 14 | N4: Takeaway | O4: Card | P4: Pasta | Q4: Chicken Alfredo | R4: 2 | S4: 5.03 | T4: 0 | U4: 5 | V4: 5 | W4: =Data!$R4*Data!$S4*(1-Data!$T4/100)*(1+Data!$U4/100) -> 10.563 | X4: =Data!$R4*Data!$S4*50% -> 5.03 | Y4: =Data!$W4-Data!$X4 -> 5.533 | Z4: =IF(COUNTIF($G$2:G4,G4)=1,1,0) -> 1
A5: ORD0019 | B5: 45672 | C5: Jan | D5: Q1 | E5: 11:30 | F5: Sunday | G5: C096 | H5: Occasional | I5: Male | J5: 18-25 | K5: William | L5: Singapore | M5: 8 | N5: Dine-In | O5: Cash | P5: Desserts | Q5: Chocolate Brownie | R5: 2 | S5: 7.77 | T5: 0 | U5: 5 | V5: 3 | W5: =Data!$R5*Data!$S5*(1-Data!$T5/100)*(1+Data!$U5/100) -> 16.317 | X5: =Data!$R5*Data!$S5*50% -> 7.77 | Y5: =Data!$W5-Data!$X5 -> 8.547 | Z5: =IF(COUNTIF($G$2:G5,G5)=1,1,0) -> 1 | AD5: Unique customers How many time customers Appears in the Dataset
A6: ORD0037 | B6: 45658 | C6: Jan | D6: Q1 | E6: 21:15 | F6: Tuesday | G6: C166 | H6: New | I6: Male | J6: 26-35 | K6: Lucas | L6: Tokyo | M6: 19 | N6: Takeaway | O6: Card | P6: Pizza | Q6: BBQ Chicken Pizza | R6: 3 | S6: 12.56 | T6: 0 | U6: 5 | V6: 4.5 | W6: =Data!$R6*Data!$S6*(1-Data!$T6/100)*(1+Data!$U6/100) -> 39.564 | X6: =Data!$R6*Data!$S6*50% -> 18.84 | Y6: =Data!$W6-Data!$X6 -> 20.724 | Z6: =IF(COUNTIF($G$2:G6,G6)=1,1,0) -> 1
A7: ORD0038 | B7: 45664 | C7: Jan | D7: Q1 | E7: 15:00 | F7: Monday | G7: C087 | H7: Occasional | I7: Male | J7: 26-35 | K7: William | L7: Singapore | M7: 15 | N7: Delivery | O7: Card | P7: Burgers | Q7: Bacon Cheeseburger | R7: 2 | S7: 13.61 | T7: 10 | U7: 5 | V7: 3 | W7: =Data!$R7*Data!$S7*(1-Data!$T7/100)*(1+Data!$U7/100) -> 25.7229 | X7: =Data!$R7*Data!$S7*50% -> 13.61 | Y7: =Data!$W7-Data!$X7 -> 12.1129 | Z7: =IF(COUNTIF($G$2:G7,G7)=1,1,0) -> 1
A8: ORD0061 | B8: 45677 | C8: Jan | D8: Q1 | E8: 16:45 | F8: Wednesday | G8: C051 | H8: New | I8: Female | J8: 26-35 | K8: Lucas | L8: Paris | M8: 14 | N8: Delivery | O8: Wallet | P8: Pasta | Q8: Spaghetti Carbonara | R8: 2 | S8: 7.15 | T8: 0 | U8: 5 | V8: 5 | W8: =Data!$R8*Data!$S8*(1-Data!$T8/100)*(1+Data!$U8/100) -> 15.015 | X8: =Data!$R8*Data!$S8*50% -> 7.15 | Y8: =Data!$W8-Data!$X8 -> 7.865 | Z8: =IF(COUNTIF($G$2:G8,G8)=1,1,0) -> 1
A9: ORD0068 | B9: 45671 | C9: Jan | D9: Q1 | E9: 12:45 | F9: Thursday | G9: C033 | H9: New | I9: Female | J9: 26-35 | K9: Noah | L9: Paris | M9: 15 | N9: Dine-In | O9: Card | P9: Desserts | Q9: Ice Cream Sundae | R9: 2 | S9: 8.68 | T9: 0 | U9: 5 | V9: 4.5 | W9: =Data!$R9*Data!$S9*(1-Data!$T9/100)*(1+Data!$U9/100) -> 18.228 | X9: =Data!$R9*Data!$S9*50% -> 8.68 | Y9: =Data!$W9-Data!$X9 -> 9.548 | Z9: =IF(COUNTIF($G$2:G9,G9)=1,1,0) -> 1 | AE9: =COUNTA(Data!$G$2:$G$490) -> 489
A10: ORD0078 | B10: 45671 | C10: Jan | D10: Q1 | E10: 15:30 | F10: Sunday | G10: C196 | H10: Occasional | I10: Male | J10: 36-50 | K10: Ethan | L10: Dubai | M10: 13 | N10: Delivery | O10: UPI | P10: Seafood | Q10: Fish Tacos | R10: 3 | S10: 5.83 | T10: 5 | U10: 5 | V10: 3 | W10: =Data!$R10*Data!$S10*(1-Data!$T10/100)*(1+Data!$U10/100) -> 17.446275 | X10: =Data!$R10*Data!$S10*50% -> 8.745 | Y10: =Data!$W10-Data!$X10 -> 8.701275 | Z10: =IF(COUNTIF($G$2:G10,G10)=1,1,0) -> 1
A11: ORD0080 | B11: 45675 | C11: Jan | D11: Q1 | E11: 16:45 | F11: Tuesday | G11: C020 | H11: New | I11: Female | J11: 36-50 | K11: Ethan | L11: Tokyo | M11: 19 | N11: Takeaway | O11: Card | P11: Desserts | Q11: Tiramisu | R11: 2 | S11: 15.03 | T11: 5 | U11: 5 | V11: 3 | W11: =Data!$R11*Data!$S11*(1-Data!$T11/100)*(1+Data!$U11/100) -> 29.98485 | X11: =Data!$R11*Data!$S11*50% -> 15.03 | Y11: =Data!$W11-Data!$X11 -> 14.95485 | Z11: =IF(COUNTIF($G$2:G11,G11)=1,1,0) -> 1
A12: ORD0082 | B12: 45683 | C12: Jan | D12: Q1 | E12: 11:15 | F12: Wednesday | G12: C115 | H12: New | I12: Male | J12: 50+ | K12: William | L12: Dubai | M12: 5 | N12: Takeaway | O12: Cash | P12: Pizza | Q12: Four Cheese Pizza | R12: 2 | S12: 6.02 | T12: 5 | U12: 5 | V12: 4.5 | W12: =Data!$R12*Data!$S12*(1-Data!$T12/100)*(1+Data!$U12/100) -> 12.0099 | X12: =Data!$R12*Data!$S12*50% -> 6.02 | Y12: =Data!$W12-Data!$X12 -> 5.9899 | Z12: =IF(COUNTIF($G$2:G12,G12)=1,1,0) -> 1
A13: ORD0086 | B13: 45658 | C13: Jan | D13: Q1 | E13: 10:15 | F13: Tuesday | G13: C042 | H13: Occasional | I13: Male | J13: 26-35 | K13: Oliver | L13: Paris | M13: 5 | N13: Delivery | O13: UPI | P13: Burgers | Q13: Bacon Cheeseburger | R13: 2 | S13: 14.79 | T13: 5 | U13: 5 | V13: 5 | W13: =Data!$R13*Data!$S13*(1-Data!$T13/100)*(1+Data!$U13/100) -> 29.50605 | X13: =Data!$R13*Data!$S13*50% -> 14.79 | Y13: =Data!$W13-Data!$X13 -> 14.71605 | Z13: =IF(COUNTIF($G$2:G13,G13)=1,1,0) -> 1
A14: ORD0088 | B14: 45674 | C14: Jan | D14: Q1 | E14: 12:15 | F14: Wednesday | G14: C181 | H14: New | I14: Female | J14: 26-35 | K14: Ethan | L14: Dubai | M14: 12 | N14: Delivery | O14: Card | P14: Seafood | Q14: Fish and Chips | R14: 2 | S14: 5.28 | T14: 5 | U14: 5 | V14: 5 | W14: =Data!$R14*Data!$S14*(1-Data!$T14/100)*(1+Data!$U14/100) -> 10.5336 | X14: =Data!$R14*Data!$S14*50% -> 5.28 | Y14: =Data!$W14-Data!$X14 -> 5.2536 | Z14: =IF(COUNTIF($G$2:G14,G14)=1,1,0) -> 1
A15: ORD0105 | B15: 45675 | C15: Jan | D15: Q1 | E15: 15:30 | F15: Monday | G15: C019 | H15: Occasional | I15: Female | J15: 18-25 | K15: Noah | L15: Singapore | M15: 20 | N15: Dine-In | O15: Card | P15: Steak | Q15: Sirloin Steak | R15: 2 | S15: 15.24 | T15: 0 | U15: 5 | V15: 4.5 | W15: =Data!$R15*Data!$S15*(1-Data!$T15/100)*(1+Data!$U15/100) -> 32.004 | X15: =Data!$R15*Data!$S15*50% -> 15.24 | Y15: =Data!$W15-Data!$X15 -> 16.764 | Z15: =IF(COUNTIF($G$2:G15,G15)=1,1,0) -> 1
A16: ORD0117 | B16: 45684 | C16: Jan | D16: Q1 | E16: 19:45 | F16: Tuesday | G16: C057 | H16: New | I16: Female | J16: 18-25 | K16: Oliver | L16: Singapore | M16: 10 | N16: Dine-In | O16: Cash | P16: Seafood | Q16: Grilled Salmon | R16: 2 | S16: 10.23 | T16: 5 | U16: 5 | V16: 3 | W16: =Data!$R16*Data!$S16*(1-Data!$T16/100)*(1+Data!$U16/100) -> 20.40885 | X16: =Data!$R16*Data!$S16*50% -> 10.23 | Y16: =Data!$W16-Data!$X16 -> 10.17885 | Z16: =IF(COUNTIF($G$2:G16,G16)=1,1,0) -> 1
A17: ORD0133 | B17: 45668 | C17: Jan | D17: Q1 | E17: 22:30 | F17: Friday | G17: C197 | H17: New | I17: Female | J17: 50+ | K17: William | L17: Paris | M17: 7 | N17: Takeaway | O17: UPI | P17: Burgers | Q17: Classic Cheeseburger | R17: 3 | S17: 7.61 | T17: 10 | U17: 5 | V17: 4.5 | W17: =Data!$R17*Data!$S17*(1-Data!$T17/100)*(1+Data!$U17/100) -> 21.57435 | X17: =Data!$R17*Data!$S17*50% -> 11.415 | Y17: =Data!$W17-Data!$X17 -> 10.15935 | Z17: =IF(COUNTIF($G$2:G17,G17)=1,1,0) -> 1
A18: ORD0138 | B18: 45671 | C18: Jan | D18: Q1 | E18: 10:30 | F18: Tuesday | G18: C100 | H18: New | I18: Male | J18: 26-35 | K18: Lucas | L18: Tokyo | M18: 20 | N18: Delivery | O18: Card | P18: Burgers | Q18: Mushroom Swiss Burger | R18: 2 | S18: 7.66 | T18: 10 | U18: 5 | V18: 4.5 | W18: =Data!$R18*Data!$S18*(1-Data!$T18/100)*(1+Data!$U18/100) -> 14.4774 | X18: =Data!$R18*Data!$S18*50% -> 7.66 | Y18: =Data!$W18-Data!$X18 -> 6.8174 | Z18: =IF(COUNTIF($G$2:G18,G18)=1,1,0) -> 1
A19: ORD0146 | B19: 45679 | C19: Jan | D19: Q1 | E19: 11:00 | F19: Wednesday | G19: C192 | H19: New | I19: Female | J19: 18-25 | K19: Oliver | L19: Tokyo | M19: 14 | N19: Delivery | O19: UPI | P19: Seafood | Q19: Garlic Butter Shrimp | R19: 2 | S19: 7.66 | T19: 5 | U19: 5 | V19: 5 | W19: =Data!$R19*Data!$S19*(1-Data!$T19/100)*(1+Data!$U19/100) -> 15.2817 | X19: =Data!$R19*Data!$S19*50% -> 7.66 | Y19: =Data!$W19-Data!$X19 -> 7.6217 | Z19: =IF(COUNTIF($G$2:G19,G19)=1,1,0) -> 1
A20: ORD0162 | B20: 45681 | C20: Jan | D20: Q1 | E20: 12:15 | F20: Thursday | G20: C182 | H20: New | I20: Male | J20: 36-50 | K20: Oliver | L20: Tokyo | M20: 19 | N20: Delivery | O20: Wallet | P20: Desserts | Q20: Chocolate Brownie | R20: 2 | S20: 5.58 | T20: 5 | U20: 5 | V20: 5 | W20: =Data!$R20*Data!$S20*(1-Data!$T20/100)*(1+Data!$U20/100) -> 11.1321 | X20: =Data!$R20*Data!$S20*50% -> 5.58 | Y20: =Data!$W20-Data!$X20 -> 5.5521 | Z20: =IF(COUNTIF($G$2:G20,G20)=1,1,0) -> 1
A21: ORD0177 | B21: 45677 | C21: Jan | D21: Q1 | E21: 13:45 | F21: Tuesday | G21: C105 | H21: Occasional | I21: Male | J21: 36-50 | K21: Noah | L21: Singapore | M21: 15 | N21: Delivery | O21: UPI | P21: Pasta | Q21: Seafood Pasta | R21: 2 | S21: 15.97 | T21: 5 | U21: 5 | V21: 5 | W21: =Data!$R21*Data!$S21*(1-Data!$T21/100)*(1+Data!$U21/100) -> 31.86015 | X21: =Data!$R21*Data!$S21*50% -> 15.97 | Y21: =Data!$W21-Data!$X21 -> 15.89015 | Z21: =IF(COUNTIF($G$2:G21,G21)=1,1,0) -> 1
... A490: ORD0489 | B490: 46004 | C490: Dec | D490: Q4 | E490: 10:15 | F490: Thursday | G490: C122 | H490: Regular | I490: Female | J490: 50+ | K490: Noah | L490: Paris | M490: 22 | N490: Dine-In | O490: UPI | P490: Desserts | Q490: Tiramisu | R490: 8 | S490: 8.32 | T490: 0 | U490: 5 | V490: 4 | W490: =Data!$R490*Data!$S490*(1-Data!$T490/100)*(1+Data!$U490/100) -> 69.888 | X490: =Data!$R490*Data!$S490*50% -> 33.28 | Y490: =Data!$W490-Data!$X490 -> 36.608 | Z490: =IF(COUNTIF($G$2:G490,G490)=1,1,0) -> 0

Sheet Project Objective
A1: PROJECT OBJECTIVE
A3: Q.1 How much total sales did we generate?
A4: Q.2 How much Profit did we generate?
A5: Q.3 Which month performed best?
A6: Q.4 Which food category generates the highest sales?
A7: Q.5 Which city generates the highest revenue?
A8: Q.6 Which waiter performs best?
A9: Q.7 Which dining type is most popular?
A10: Q.8 Which payment method is used most?
A11: Q.9 Which customer type contributes the most sales?
A12: Q. 10 Which items are selling the most?
A13: Q.11 How are customers rating the restaurant?
... A34: Q5. How many unique customers?
A36: =COUNTA(_xlfn.UNIQUE(Data!$G$2:$G$490)) -> 180
A38: Q6. How many unique orders?
A40: =COUNTA(_xlfn.UNIQUE(Data!$A$2:$A$490)) -> 455
A42: Q7. What is total sales?
A44: =SUM(Data!$W$2:$W$490) -> 20694.485
A46: Q8. What is total profit?
A48: =SUM(Data!$Y$2:$Y$490) -> 10338.27
A50: Q9. Which city has the highest sales?
A52: {=_xlfn.LET(_xlpm.c,_xlfn.UNIQUE(Data!$L$2:$L$490),_xlpm.s,SUMIF(Data!$L$2:$L$490,_xlpm.c,Data!$W$2:$W$490),_xlfn.XLOOKUP(MAX(_xlpm.s),_xlpm.s,_xlpm.c))} -> Dubai
A54: Q10. Which food category has the highest sales?
A56: Pasta.
A58: Q11. Which month has the highest sales?
A60: December
A62: Q12. Which quarter performs best?
A64: Q4.
A66: Q13. Which dining type has the highest sales?
A68: Dine-In.
A70: Q14. Which payment method has the highest sales?
A72: Card.
A74: Q15. Which customer type has the highest sales?
A76: New customers.
... A88: Approximately 4 out of 5.

Sheet Analysis
D2: MONTHLY SALES TREND | G2: MONTHLY PROFIT TREND | J2: SALES BY CATEGORY | M2: CITY WISE SALES | P2: TOP 5 QTY SELLING ITEMS | S2: TOP 5 WAITERS BY SALE | W2: PAYMENT METHOD CATEGORY | Z2: DINING TYPE DISTRIBUTION | AC2: CUSTOMER TYPES SALES | AH2: AVG RATINGS BY CATEGORY
A3: Values | D3: Row Labels | E3: Sum of Total sales | G3: Row Labels | H3: Sum of Profit | J3: Row Labels | K3: Sum of Total sales | M3: Row Labels | N3: Sum of Total sales | P3: Row Labels | Q3: Sum of Quantity | S3: Row Labels | T3: Sum of Total sales | W3: Row Labels | X3: Sum of Total sales | Z3: Row Labels | AA3: Sum of Total sales | AC3: Row Labels | AD3: Sum of Total sales | AH3: Row Labels | AI3: Average of Rating
A4: Sum of Total sales | B4: 20694.485 | D4: Jan | E4: 934.97145 | G4: Jan | H4: 468.71645 | J4: Burgers | K4: 3242.7617 | M4: Dubai | N4: 5403.7137 | P4: Lasagna | Q4: 89 | S4: Noah | T4: 4503.5713 | W4: Card | X4: 6264.8481 | Z4: Delivery | AA4: 6606.0503 | AC4: New | AD4: 11636.808 | AH4: Burgers | AI4: 4.1277108
A5: Count of Order ID | B5: 489 | D5: Feb | E5: 1146.8111 | G5: Feb | H5: 568.97605 | J5: Desserts | K5: 3284.4152 | M5: Singapore | N5: 4945.5614 | P5: Tiramisu | Q5: 89 | S5: Lucas | T5: 4377.3324 | W5: Cash | X5: 5620.4584 | Z5: Dine-In | AA5: 8333.0861 | AC5: Occasional | AD5: 857.11447 | AH5: Desserts | AI5: 4.0447368
A6: Sum of Profit | B6: 10338.27 | D6: Mar | E6: 1067.8873 | G6: Mar | H6: 532.57727 | J6: Pasta | K6: 3759.2987 | M6: Tokyo | N6: 4855.683 | P6: Ribeye Steak | Q6: 93 | S6: Ethan | T6: 4106.5673 | W6: UPI | X6: 3842.2608 | Z6: Takeaway | AA6: 5755.3487 | AC6: Regular | AD6: 8200.563 | AH6: Pasta | AI6: 3.9517647
A7: Sum of Unique Customers | B7: 180 | D7: Apr | E7: 1356.1601 | G7: Apr | H7: 674.77005 | J7: Pizza | K7: 3285.3345 | M7: Paris | N7: 3804.5511 | P7: Grilled Salmon | Q7: 96 | S7: Oliver | T7: 4037.6254 | W7: Wallet | X7: 4966.9179 | Z7: Grand Total | AA7: 20694.485 | AC7: Grand Total | AD7: 20694.485 | AH7: Pizza | AI7: 3.9542169
A8: Average of Rating | B8: 3.9981595 | D8: May | E8: 1429.0952 | G8: May | H8: 709.93515 | J8: Seafood | K8: 3490.1779 | M8: Sydney | N8: 1006.8382 | P8: BBQ Chicken Burger | Q8: 97 | S8: William | T8: 3669.3888 | W8: Grand Total | X8: 20694.485 | AH8: Seafood | AI8: 3.9597561
D9: Jun | E9: 1571.4101 | G9: Jun | H9: 779.40505 | J9: Steak | K9: 3632.4971 | M9: Toronto | N9: 678.13777 | P9: Grand Total | Q9: 464 | S9: Grand Total | T9: 20694.485 | AH9: Steak | AI9: 3.95375
D10: Jul | E10: 1258.4796 | G10: Jul | H10: 626.1346 | J10: Grand Total | K10: 20694.485 | M10: Grand Total | N10: 20694.485 | AH10: Grand Total | AI10: 3.9981595
A11: Total Sales | B11: =GETPIVOTDATA("Sum of Total sales",$A$3) -> 20694.485 | D11: Aug | E11: 1851.4981 | G11: Aug | H11: 925.28308
A12: Total Orders | B12: =GETPIVOTDATA("Count of Order ID",$A$3) -> 489 | D12: Sep | E12: 2246.3364 | G12: Sep | H12: 1118.6664
A13: Profit | B13: =GETPIVOTDATA("Sum of Profit",$A$3) -> 10338.27 | D13: Oct | E13: 2144.5736 | G13: Oct | H13: 1063.7635
A14: Customers | B14: =GETPIVOTDATA("Sum of Unique Customers",$A$3) -> 180 | D14: Nov | E14: 2453.2074 | G14: Nov | H14: 1232.8774
A15: Avg Order Value | B15: =B11/B12 -> 42.320011 | D15: Dec | E15: 3234.0551 | G15: Dec | H15: 1637.1651
A16: Avg Rating | B16: =GETPIVOTDATA("Average of Rating",$A$3) -> 3.9981595 | D16: Grand Total | E16: 20694.485 | G16: Grand Total | H16: 10338.27

Sheet DashBoard
E1: #VALUE!
AB30: #VALUE!

Sheet Detail1
A1: Details for Count of Order ID
A3: Order ID | B3: Order date | C3: Month | D3: Quarter | E3: Order Time | F3: Day | G3: Customer ID | H3: Customer Type | I3: Gender | J3: Age Group | K3: Waiter | L3: City | M3: Table No | N3: Dining Type | O3: Payment Method | P3: Food Category | Q3: Item Name | R3: Quantity | S3: Unit Price | T3: Discount % | U3: Tax % | V3: Rating | W3: Total sales | X3: Cost | Y3: Profit | Z3: Unique Customers
A4: ORD0010 | B4: 45685 | C4: Jan | D4: Q1 | E4: 20:45 | F4: Saturday | G4: C040 | H4: Occasional | I4: Female | J4: 18-25 | K4: Lucas | L4: Singapore | M4: 7 | N4: Delivery | O4: Wallet | P4: Seafood | Q4: Fish Tacos | R4: 2 | S4: 3.08 | T4: 10 | U4: 5 | V4: 3 | W4: 5.8212 | X4: 3.08 | Y4: 2.7412 | Z4: 1
A5: ORD0013 | B5: 45662 | C5: Jan | D5: Q1 | E5: 12:00 | F5: Saturday | G5: C148 | H5: New | I5: Female | J5: 26-35 | K5: Ethan | L5: Tokyo | M5: 17 | N5: Dine-In | O5: Card | P5: Desserts | Q5: Chocolate Lava Cake | R5: 2 | S5: 5.67 | T5: 0 | U5: 5 | V5: 4.5 | W5: 11.907 | X5: 5.67 | Y5: 6.237 | Z5: 1
A6: ORD0015 | B6: 45677 | C6: Jan | D6: Q1 | E6: 11:00 | F6: Sunday | G6: C007 | H6: Occasional | I6: Female | J6: 26-35 | K6: Lucas | L6: Paris | M6: 14 | N6: Takeaway | O6: Card | P6: Pasta | Q6: Chicken Alfredo | R6: 2 | S6: 5.03 | T6: 0 | U6: 5 | V6: 5 | W6: 10.563 | X6: 5.03 | Y6: 5.533 | Z6: 1
A7: ORD0019 | B7: 45672 | C7: Jan | D7: Q1 | E7: 11:30 | F7: Sunday | G7: C096 | H7: Occasional | I7: Male | J7: 18-25 | K7: William | L7: Singapore | M7: 8 | N7: Dine-In | O7: Cash | P7: Desserts | Q7: Chocolate Brownie | R7: 2 | S7: 7.77 | T7: 0 | U7: 5 | V7: 3 | W7: 16.317 | X7: 7.77 | Y7: 8.547 | Z7: 1
A8: ORD0037 | B8: 45658 | C8: Jan | D8: Q1 | E8: 21:15 | F8: Tuesday | G8: C166 | H8: New | I8: Male | J8: 26-35 | K8: Lucas | L8: Tokyo | M8: 19 | N8: Takeaway | O8: Card | P8: Pizza | Q8: BBQ Chicken Pizza | R8: 3 | S8: 12.56 | T8: 0 | U8: 5 | V8: 4.5 | W8: 39.564 | X8: 18.84 | Y8: 20.724 | Z8: 1
A9: ORD0038 | B9: 45664 | C9: Jan | D9: Q1 | E9: 15:00 | F9: Monday | G9: C087 | H9: Occasional | I9: Male | J9: 26-35 | K9: William | L9: Singapore | M9: 15 | N9: Delivery | O9: Card | P9: Burgers | Q9: Bacon Cheeseburger | R9: 2 | S9: 13.61 | T9: 10 | U9: 5 | V9: 3 | W9: 25.7229 | X9: 13.61 | Y9: 12.1129 | Z9: 1
A10: ORD0061 | B10: 45677 | C10: Jan | D10: Q1 | E10: 16:45 | F10: Wednesday | G10: C051 | H10: New | I10: Female | J10: 26-35 | K10: Lucas | L10: Paris | M10: 14 | N10: Delivery | O10: Wallet | P10: Pasta | Q10: Spaghetti Carbonara | R10: 2 | S10: 7.15 | T10: 0 | U10: 5 | V10: 5 | W10: 15.015 | X10: 7.15 | Y10: 7.865 | Z10: 1
A11: ORD0068 | B11: 45671 | C11: Jan | D11: Q1 | E11: 12:45 | F11: Thursday | G11: C033 | H11: New | I11: Female | J11: 26-35 | K11: Noah | L11: Paris | M11: 15 | N11: Dine-In | O11: Card | P11: Desserts | Q11: Ice Cream Sundae | R11: 2 | S11: 8.68 | T11: 0 | U11: 5 | V11: 4.5 | W11: 18.228 | X11: 8.68 | Y11: 9.548 | Z11: 1
A12: ORD0078 | B12: 45671 | C12: Jan | D12: Q1 | E12: 15:30 | F12: Sunday | G12: C196 | H12: Occasional | I12: Male | J12: 36-50 | K12: Ethan | L12: Dubai | M12: 13 | N12: Delivery | O12: UPI | P12: Seafood | Q12: Fish Tacos | R12: 3 | S12: 5.83 | T12: 5 | U12: 5 | V12: 3 | W12: 17.446275 | X12: 8.745 | Y12: 8.701275 | Z12: 1
A13: ORD0080 | B13: 45675 | C13: Jan | D13: Q1 | E13: 16:45 | F13: Tuesday | G13: C020 | H13: New | I13: Female | J13: 36-50 | K13: Ethan | L13: Tokyo | M13: 19 | N13: Takeaway | O13: Card | P13: Desserts | Q13: Tiramisu | R13: 2 | S13: 15.03 | T13: 5 | U13: 5 | V13: 3 | W13: 29.98485 | X13: 15.03 | Y13: 14.95485 | Z13: 1
A14: ORD0082 | B14: 45683 | C14: Jan | D14: Q1 | E14: 11:15 | F14: Wednesday | G14: C115 | H14: New | I14: Male | J14: 50+ | K14: William | L14: Dubai | M14: 5 | N14: Takeaway | O14: Cash | P14: Pizza | Q14: Four Cheese Pizza | R14: 2 | S14: 6.02 | T14: 5 | U14: 5 | V14: 4.5 | W14: 12.0099 | X14: 6.02 | Y14: 5.9899 | Z14: 1
A15: ORD0086 | B15: 45658 | C15: Jan | D15: Q1 | E15: 10:15 | F15: Tuesday | G15: C042 | H15: Occasional | I15: Male | J15: 26-35 | K15: Oliver | L15: Paris | M15: 5 | N15: Delivery | O15: UPI | P15: Burgers | Q15: Bacon Cheeseburger | R15: 2 | S15: 14.79 | T15: 5 | U15: 5 | V15: 5 | W15: 29.50605 | X15: 14.79 | Y15: 14.71605 | Z15: 1
... A492: ORD0489 | B492: 46004 | C492: Dec | D492: Q4 | E492: 10:15 | F492: Thursday | G492: C122 | H492: Regular | I492: Female | J492: 50+ | K492: Noah | L492: Paris | M492: 22 | N492: Dine-In | O492: UPI | P492: Desserts | Q492: Tiramisu | R492: 8 | S492: 8.32 | T492: 0 | U492: 5 | V492: 4 | W492: 69.888 | X492: 33.28 | Y492: 36.608 | Z492: 0
